JAAT/JAAT.py
JAAT/__init__.py
JAAT/data/SOC_map.json
JAAT/data/Task_DWA.csv
JAAT/data/keywords.json
JAAT/data/lexicon_parse.py
JAAT/data/lexiconwex2023.csv
JAAT/data/skills.csv
JAAT/data/sub_dict.json
JAAT/data/title_embeddings.pickle
JAAT/models/CitizenshipReq.lzma
JAAT/models/GovContract.lzma
JAAT/models/VisaExclude.lzma
JAAT/models/VisaInclude.lzma
JAAT/models/WorkAuthReq.lzma
JAAT/models/driverslicense.lzma
JAAT/models/ind_contractor.lzma
JAAT/models/proflicenses.lzma
JAAT/models/wfh.lzma
JAAT/models/yesunion.lzma
jaat-0.5.0.dist-info/LICENSE
jaat-0.5.0.dist-info/METADATA
jaat-0.5.0.dist-info/WHEEL
jaat-0.5.0.dist-info/top_level.txt
jaat-0.5.0.dist-info/RECORD
