Metadata-Version: 2.1
Name: JAAT
Version: 0.5.0
Summary: Repository for JAAT: efficient and accurate analysis of job ads for task matching, title matching, firm name extraction, attribute classification, and wage extraction.
Author-email: Stephen Meisenbacher <stephen.meisenbacher@tum.de>, Peter Norlander <pnorlander@luc.edu>
Maintainer-email: Stephen Meisenbacher <stephen.meisenbacher@tum.de>
License: MIT License
Project-URL: Homepage, https://github.com/Job-Ad-Research-at-QSB-LUC/JAAT
Project-URL: Documentation, https://github.com/Job-Ad-Research-at-QSB-LUC/JAAT
Project-URL: Repository, https://github.com/Job-Ad-Research-at-QSB-LUC/JAAT
Project-URL: Issues, https://github.com/Job-Ad-Research-at-QSB-LUC/JAAT/issues
Keywords: text analysis,text classification,semantic matching
Classifier: Programming Language :: Python :: 3
Classifier: License :: OSI Approved :: MIT License
Classifier: Operating System :: OS Independent
Requires-Python: >=3.8
License-File: LICENSE
Requires-Dist: importlib-resources
Requires-Dist: nltk
Requires-Dist: pandas
Requires-Dist: psutil
Requires-Dist: sentence-transformers
Requires-Dist: torch
Requires-Dist: tqdm
Requires-Dist: transformers
Requires-Dist: xlrd
Requires-Dist: swifter
Requires-Dist: pure-predict
Requires-Dist: compress-pickle
Requires-Dist: syllables
